LICENSE
MANIFEST.in
README.rst
pyproject.toml
setup.cfg
setup.py
uberlogging/__init__.py
uberlogging.egg-info/PKG-INFO
uberlogging.egg-info/SOURCES.txt
uberlogging.egg-info/dependency_links.txt
uberlogging.egg-info/requires.txt
uberlogging.egg-info/top_level.txt