Metadata-Version: 1.1
Name: uberlogging
Version: 0.7.0
Summary: Highly opinionated logging configurator
Home-page: https://github.com/haizaar/uberlogging
Author: Zaar Hai
Author-email: haizaar@haizaar.com
License:                                  Apache License
